[
  {
    "name": "Burgers",
    "subcategories": [
      "Krusty Burger Classics",
      "Veggie Burgers",
      "Specialty Burgers",
      "Classic Burgers"
    ],
    "icon": "hamburger",
    "banner": "https://firebasestorage.googleapis.com/v0/b/krusty-burger-app.appspot.com/o/banner6_500.png?alt=media&token=9d284ac1-6f7c-469f-86cc-49facd058270"
  },
  {
    "name": "Hot Dogs",
    "subcategories": [
      "Classic Hot Dogs",
      "Chili Cheese Dogs",
      "Jumbo Dogs",
      "Specialty Hot Dogs"
    ],
    "icon": "food-hot-dog",
    "banner": "https://firebasestorage.googleapis.com/v0/b/krusty-burger-app.appspot.com/o/category-banner-hotdogs_500.png?alt=media&token=a3deadbf-9f32-4558-8a77-197ac797fe7e"
  },
  {
    "name": "Sandwiches",
    "subcategories": [
      "BLT Sandwiches",
      "Fish Fillet Sandwiches",
      "Veggie Sandwiches"
    ],
    "icon": "food",
    "banner": "https://firebasestorage.googleapis.com/v0/b/krusty-burger-app.appspot.com/o/category-banner-sandwitch_500.png?alt=media&token=ef5d1712-5da0-49a5-a3b1-4060f74e9a62"
  },
  {
    "name": "Chicken",
    "subcategories": [
      "Crispy Chicken",
      "Grilled Chicken",
      "Chicken Wings"
    ],
    "icon": "food-drumstick",
    "banner": "https://firebasestorage.googleapis.com/v0/b/krusty-burger-app.appspot.com/o/category-banner-chicken_500.png?alt=media&token=2deda072-f82a-4bb5-8236-224d42210df7"
  },
  {
    "name": "Breakfast",
    "subcategories": [
      "Breakfast Platters",
      "Breakfast Burritos",
      "Pancakes & Waffles"
    ],
    "icon": "food-croissant",
    "banner": "https://firebasestorage.googleapis.com/v0/b/krusty-burger-app.appspot.com/o/category-banner-breakfast_500.png?alt=media&token=174784cb-d139-4dfe-beff-16094ea6ce51"
  },
  {
    "name": "Desserts",
    "subcategories": [
      "Milkshakes",
      "Sweet Treats",
      "Ice Cream"
    ],
    "icon": "ice-cream",
    "banner": "https://firebasestorage.googleapis.com/v0/b/krusty-burger-app.appspot.com/o/category-banner-desserts_500.png?alt=media&token=efd67af9-908b-4699-924f-48c1cb8cd9c8"
  },
  {
    "name": "Side Options",
    "subcategories": [],
    "icon": "french-fries",
    "banner": "https://firebasestorage.googleapis.com/v0/b/krusty-burger-app.appspot.com/o/category-banner-fries_500.png?alt=media&token=6387f6c9-fe31-4f3f-a8c5-61618d76f894"
  },
  {
    "name": "Beverages",
    "subcategories": [
      "Sodas"
    ],
    "icon": "beer",
    "banner": "https://firebasestorage.googleapis.com/v0/b/krusty-burger-app.appspot.com/o/Absolut_Krusty_500.png?alt=media&token=3a0efdc6-9ece-49d6-b542-5f4c25301d6d"
  }
]